conda_minify/__init__.py
conda_minify/__main__.py
conda_minify/__version__.py
conda_minify/cli.py
conda_minify/environment.py
conda_minify/graph.py
conda_minify-0.1.2.dist-info/LICENSE
conda_minify-0.1.2.dist-info/METADATA
conda_minify-0.1.2.dist-info/WHEEL
conda_minify-0.1.2.dist-info/entry_points.txt
conda_minify-0.1.2.dist-info/top_level.txt
conda_minify-0.1.2.dist-info/RECORD
