Metadata-Version: 2.1
Name: conda-minify
Version: 0.1.2
Summary: A simple library to create minified or relaxed versions of Conda environment specs for cross-platform sharing.
Home-page: https://github.com/jamespreed/conda-minify
Author: James Reed
License: UNKNOWN
Keywords: conda virtual environment yaml
Platform: UNKNOWN
Classifier: Intended Audience :: Developers
Classifier: Intended Audience :: Science/Research
Classifier: Topic :: Software Development :: Build Tools
Classifier: License :: OSI Approved :: MIT License
Classifier: Programming Language :: Python :: 3
Classifier: Programming Language :: Python :: 3.4
Classifier: Programming Language :: Python :: 3.5
Classifier: Programming Language :: Python :: 3.6
Classifier: Programming Language :: Python :: 3.7
Classifier: Programming Language :: Python :: 3.8
Requires-Python: >=3.4, <4
Requires-Dist: conda (>=4.3.0)
Requires-Dist: pyyaml (>3.0)
